pynocular/__init__.py
pynocular/aiopg_transaction.py
pynocular/config.py
pynocular/database_model.py
pynocular/db_util.py
pynocular/engines.py
pynocular/exceptions.py
pynocular/nested_database_model.py
pynocular/patch_models.py
pynocular-0.19.0.dist-info/LICENSE.md
pynocular-0.19.0.dist-info/WHEEL
pynocular-0.19.0.dist-info/METADATA
pynocular-0.19.0.dist-info/RECORD
