Metadata-Version: 2.1
Name: pynocular
Version: 0.19.0
Summary: Lightweight ORM that lets you query your database using Pydantic models and asyncio
Home-page: https://github.com/NarrativeScience/pynocular
License: BSD-3-Clause
Author: RJ Santana
Author-email: ssantana@narrativescience.com
Requires-Python: >=3.6.5,<4.0.0
Classifier: License :: OSI Approved :: BSD License
Classifier: Programming Language :: Python :: 3
Classifier: Programming Language :: Python :: 3.10
Classifier: Programming Language :: Python :: 3.7
Classifier: Programming Language :: Python :: 3.8
Classifier: Programming Language :: Python :: 3.9
Requires-Dist: aenum (>=3.1.0,<4.0.0)
Requires-Dist: aiocontextvars (>=0.2.2,<0.3.0)
Requires-Dist: aiopg[sa] (>=1.3.1,<2.0.0)
Requires-Dist: pydantic (>=1.6,<2.0)
Project-URL: Repository, https://github.com/NarrativeScience/pynocular
